djangocms_rest/__init__.py
djangocms_rest/apps.py
djangocms_rest/cms_config.py
djangocms_rest/cms_toolbars.py
djangocms_rest/middleware.py
djangocms_rest/permissions.py
djangocms_rest/plugin_rendering.py
djangocms_rest/schemas.py
djangocms_rest/urls.py
djangocms_rest/utils.py
djangocms_rest/views.py
djangocms_rest/views_base.py
djangocms_rest/serializers/__init__.py
djangocms_rest/serializers/languages.py
djangocms_rest/serializers/menus.py
djangocms_rest/serializers/pages.py
djangocms_rest/serializers/placeholders.py
djangocms_rest/serializers/plugins.py
djangocms_rest/serializers/utils/__init__.py
djangocms_rest/serializers/utils/cache.py
djangocms_rest/serializers/utils/render.py
djangocms_rest/static/djangocms_rest/highlight.css
djangocms_rest-1.0.0.dist-info/licenses/LICENSE
djangocms_rest-1.0.0.dist-info/METADATA
djangocms_rest-1.0.0.dist-info/WHEEL
djangocms_rest-1.0.0.dist-info/top_level.txt
djangocms_rest-1.0.0.dist-info/RECORD
