Metadata-Version: 2.4
Name: djangocms-rest
Version: 1.0.0
Summary: API endpoints for django CMS
Author-email: Fabian Braun <fsbraun@gmx.de>
Maintainer-email: Django CMS Association and contributors <info@django-cms.org>
License-Expression: BSD-3-Clause
Project-URL: Homepage, https://github.com/django-cms/djangocms-rest
Project-URL: Repository, https://github.com/django-cms/djangocms-rest
Classifier: Development Status :: 5 - Production/Stable
Classifier: Environment :: Web Environment
Classifier: Framework :: Django
Classifier: Framework :: Django :: 4.2
Classifier: Framework :: Django :: 5.0
Classifier: Framework :: Django :: 5.1
Classifier: Framework :: Django :: 5.2
Classifier: Framework :: Django :: 6.0
Classifier: Framework :: Django CMS
Classifier: Framework :: Django CMS :: 4.0
Classifier: Framework :: Django CMS :: 4.1
Classifier: Framework :: Django CMS :: 5.0
Classifier: Intended Audience :: Developers
Classifier: Operating System :: OS Independent
Classifier: Programming Language :: Python
Classifier: Programming Language :: Python :: 3
Classifier: Programming Language :: Python :: 3.10
Classifier: Programming Language :: Python :: 3.11
Classifier: Programming Language :: Python :: 3.12
Classifier: Programming Language :: Python :: 3.13
Classifier: Programming Language :: Python :: 3.14
Classifier: Topic :: Internet :: WWW/HTTP
Classifier: Topic :: Internet :: WWW/HTTP :: Dynamic Content
Classifier: Topic :: Software Development
Classifier: Topic :: Software Development :: Libraries
Requires-Python: >=3.10
License-File: LICENSE
Requires-Dist: django-cms>=5.0.0a1
Requires-Dist: djangorestframework
Requires-Dist: djangocms-link>=5.0.0
Requires-Dist: djangocms-text>=0.8.0
Requires-Dist: djangocms-versioning>=2.1.0
Requires-Dist: pytest-cov>=6.0.0
Requires-Dist: pytest-django>=4.10.0
Provides-Extra: dev
Requires-Dist: pytest>=7.3.1; extra == "dev"
Requires-Dist: pytest-django>=4.5.2; extra == "dev"
Requires-Dist: mypy>=1.3.0; extra == "dev"
Requires-Dist: django-stubs>=4.2.3; extra == "dev"
Requires-Dist: djangorestframework-stubs>=3.14.0; extra == "dev"
Dynamic: license-file
